{
  "id": "桥区通航净空尺度",
  "name_zh": "桥区通航净空尺度",
  "name_en": "桥区通航净空尺度",
  "description": "计算跨越航道建筑物的通航净空高度和宽度 (Calculate clearance height and width)",
  "mtime": 1768705028.4321272,
  "steps": [
    {
      "id": "step_1",
      "name": "明确引用规范内容",
      "description": "参考《海港水文规范》第3.1节和2.1节，确定通航净空高度和净空宽度的取值标准。",
      "tool": "knowledge_search",
      "inputs": {
        "document": "《海港水文规范》.md",
        "section": "3.1, 2.1"
      },
      "outputs": {},
      "notes": "",
      "analysis_status": "analyzed"
    },
    {
      "id": "step_2",
      "name": "核心参数解析与确定",
      "description": "解析并确定H_air、H_safe、W和K等核心参数的值。",
      "tool": "auto",
      "inputs": {
        "context": "已知条件"
      },
      "outputs": {
        "H_air": "H_air",
        "H_safe": "H_safe",
        "W": "W",
        "K": "K"
      },
      "notes": "若H_air缺失，需提示用户：请提供代表船型的水线以上高度(Air Draft)。H_safe根据水域环境判断：开敞海域、波浪大、重要航道 → 4.0m；其他情况 → 2.0m。W继承上一环节的通航宽度结果。K优先由用户输入，否则根据DWT和环境推荐：DWT≥10万吨或环境=开敞/风浪大 → K=1.8；环境=掩护良好 → K=1.5；其他 → K=1.6~1.7。",
      "analysis_status": "analyzed"
    },
    {
      "id": "step_3",
      "name": "最终结果计算",
      "description": "根据公式计算净空高度和净空宽度。",
      "tool": "calculator",
      "inputs": {
        "H_air": "${H_air}",
        "H_safe": "${H_safe}",
        "修正项": "0",
        "K": "${K}",
        "W": "${W}"
      },
      "outputs": {
        "H_clearance": "H_clearance",
        "B": "B"
      },
      "notes": "H_clearance = H_air + H_safe + 修正项；B = K × W。",
      "analysis_status": "analyzed"
    },
    {
      "id": "step_4",
      "name": "成果输出",
      "description": "输出净空高度、净空宽度、H_air、H_safe、W、K等参数。",
      "tool": "user_input",
      "inputs": {
        "H_clearance": "${H_clearance}",
        "B": "${B}",
        "H_air": "${H_air}",
        "H_safe": "${H_safe}",
        "W": "${W}",
        "K": "${K}"
      },
      "outputs": {},
      "notes": "列出所有计算结果参数。",
      "analysis_status": "analyzed"
    }
  ]
}